fr_torrent_search/__init__.py
fr_torrent_search/__main__.py
fr_torrent_search/conftest.py
fr_torrent_search/fastapi_server.py
fr_torrent_search/mcp_server.py
fr_torrent_search/test_mcp_server.py
fr_torrent_search/wrapper/__init__.py
fr_torrent_search/wrapper/api_client.py
fr_torrent_search/wrapper/models.py
fr_torrent_search/wrapper/utils.py
fr_torrent_search/wrapper/api/__init__.py
fr_torrent_search/wrapper/api/base.py
fr_torrent_search/wrapper/api/la_cale.py
fr_torrent_search/wrapper/api/ygg_torrent.py
fr_torrent_search_mcp-1.0.7.dist-info/METADATA
fr_torrent_search_mcp-1.0.7.dist-info/WHEEL
fr_torrent_search_mcp-1.0.7.dist-info/entry_points.txt
fr_torrent_search_mcp-1.0.7.dist-info/licenses/LICENSE
fr_torrent_search_mcp-1.0.7.dist-info/RECORD
