Metadata-Version: 2.4
Name: fr-torrent-search-mcp
Version: 1.0.7
Summary: FR Torrent MCP Server
Project-URL: Repository, https://github.com/philogicae/fr-torrent-search-mcp
Project-URL: Release, https://github.com/philogicae/fr-torrent-search-mcp/releases
Project-URL: DeepWiki, https://deepwiki.com/philogicae/fr-torrent-search-mcp
Author: philogicae
License-Expression: MIT
License-File: LICENSE
Requires-Python: <4.0,>=3.10
Requires-Dist: bencodepy
Requires-Dist: fastapi
Requires-Dist: fastmcp<3
Requires-Dist: pydantic
Requires-Dist: python-dotenv
Requires-Dist: requests
Requires-Dist: uvicorn
